ninja_cursor_pagination/__init__.py
django_ninja_cursor_pagination-0.1.0.dist-info/METADATA
django_ninja_cursor_pagination-0.1.0.dist-info/WHEEL
django_ninja_cursor_pagination-0.1.0.dist-info/licenses/LICENSE
django_ninja_cursor_pagination-0.1.0.dist-info/RECORD
